python_fortress/__init__.py
python_fortress/fortress.py
python_fortress-1.1.0.dist-info/METADATA
python_fortress-1.1.0.dist-info/WHEEL
python_fortress-1.1.0.dist-info/top_level.txt
python_fortress-1.1.0.dist-info/RECORD
