Metadata-Version: 2.1
Name: python-fortress
Version: 1.1.0
Summary: A Python module to securely interact with passfortress.com API for retrieving and loading environment variables from a remote .env file.
Home-page: https://github.com/magestree/python_fortress
Author: Magestree Network S.L.
Author-email: erick.hernandez@magestree.com
License: UNKNOWN
Platform: UNKNOWN
Classifier: Programming Language :: Python :: 3
Classifier: License :: OSI Approved :: MIT License
Classifier: Operating System :: OS Independent
Requires-Dist: requests (<3,>=2.27)
Requires-Dist: python-dotenv (<1,>=0.20)
